{
  "@context": "http://iiif.io/api/presentation/3/context.json",
  "id": "https://raw.githubusercontent.com/altomator/IIIF/main/collection/presse_feminine/cb32817646w-1929.json",
  "type": "Collection",
  "label": { "fr": [ "Modes (Les) (1929)" ], "en": [ "Modes (Les) (1929)" ] },
  "description": { "fr": [ "Cette collection regroupe tous les fascicules du titre Modes (Les) pour l'ann&#xE9;e 1929" ], "en": [ "This collection gathers all the issues of the title Modes (Les) for the year 1929" ] },
  "attribution": "BnF - Gallica, gallica.bnf.fr",
  "license": "https://gallica.bnf.fr/edit/und/conditions-dutilisation-des-contenus-de-gallica",
  "logo": "https://gallica.bnf.fr/mbImage/logos/logo-bnf.png",
  "homepage": [
    {
      "id": "https://gallica.bnf.fr/ark:/12148/cb32817646w/date1929",
      "type": "Text",
      "label": { "fr": [ "Périodique Gallica : Modes (Les) (1929)" ],"en": [ "Gallica periodical: Modes (Les) (1929)" ] },
      "format": "text/html",
      "language": [ "fr" ]
    }
  ],
  "related": [{
			"id": "https://gallica.bnf.fr/ark:/12148/cb32817646w/date1929",
			"format": "text/html",
			"label": { "fr": [ "Périodique Gallica : Modes (Les) (1929)" ],"en": [ "Gallica periodical: Modes (Les) (1929)" ] }
		}],
  "items": [
{
          "id": "https://gallica.bnf.fr/iiif/ark:/12148/bpt6k6543256h/manifest.json",
          "label": "Modes (Les) ( août 1929)",
          "type": "Manifest",
          "navDate": "1929-01-01"
       },{
          "id": "https://gallica.bnf.fr/iiif/ark:/12148/bpt6k6543254p/manifest.json",
          "label": "Modes (Les) ( juin 1929)",
          "type": "Manifest",
          "navDate": "1929-01-01"
       },{
          "id": "https://gallica.bnf.fr/iiif/ark:/12148/bpt6k6543258b/manifest.json",
          "label": "Modes (Les) ( octobre 1929)",
          "type": "Manifest",
          "navDate": "1929-01-01"
       },{
          "id": "https://gallica.bnf.fr/iiif/ark:/12148/bpt6k65432553/manifest.json",
          "label": "Modes (Les) ( juillet 1929)",
          "type": "Manifest",
          "navDate": "1929-01-01"
       },{
          "id": "https://gallica.bnf.fr/iiif/ark:/12148/bpt6k65432538/manifest.json",
          "label": "Modes (Les) ( mai 1929)",
          "type": "Manifest",
          "navDate": "1929-01-01"
       },{
          "id": "https://gallica.bnf.fr/iiif/ark:/12148/bpt6k6543260d/manifest.json",
          "label": "Modes (Les) ( décembre 1929)",
          "type": "Manifest",
          "navDate": "1929-01-01"
       },{
          "id": "https://gallica.bnf.fr/iiif/ark:/12148/bpt6k6543251f/manifest.json",
          "label": "Modes (Les) ( mars 1929)",
          "type": "Manifest",
          "navDate": "1929-01-01"
       },{
          "id": "https://gallica.bnf.fr/iiif/ark:/12148/bpt6k6543252v/manifest.json",
          "label": "Modes (Les) ( avril 1929)",
          "type": "Manifest",
          "navDate": "1929-01-01"
       },{
          "id": "https://gallica.bnf.fr/iiif/ark:/12148/bpt6k65432501/manifest.json",
          "label": "Modes (Les) ( février 1929)",
          "type": "Manifest",
          "navDate": "1929-01-01"
       },{
          "id": "https://gallica.bnf.fr/iiif/ark:/12148/bpt6k6543257x/manifest.json",
          "label": "Modes (Les) ( septembre 1929)",
          "type": "Manifest",
          "navDate": "1929-01-01"
       },{
          "id": "https://gallica.bnf.fr/iiif/ark:/12148/bpt6k6543249c/manifest.json",
          "label": "Modes (Les) ( janvier 1929)",
          "type": "Manifest",
          "navDate": "1929-01-01"
       },{
          "id": "https://gallica.bnf.fr/iiif/ark:/12148/bpt6k6543259r/manifest.json",
          "label": "Modes (Les) ( novembre 1929)",
          "type": "Manifest",
          "navDate": "1929-01-01"
       }]
    }